pst/__init__.py
pst/main.py
pst/typing.py
pst/_kernels/stacked_batch_chamfer_distance.py
pst/data/__init__.py
pst/data/_types.py
pst/data/config.py
pst/data/dataset.py
pst/data/graph.py
pst/data/loader.py
pst/data/modules.py
pst/data/split.py
pst/data/utils.py
pst/embed/__init__.py
pst/embed/data.py
pst/embed/main.py
pst/embed/model.py
pst/embed/writer.py
pst/nn/__init__.py
pst/nn/base.py
pst/nn/config.py
pst/nn/layer_drop.py
pst/nn/layers.py
pst/nn/models.py
pst/nn/modules.py
pst/nn/utils/__init__.py
pst/nn/utils/attention.py
pst/nn/utils/distance.py
pst/nn/utils/loss.py
pst/nn/utils/mask.py
pst/nn/utils/norm.py
pst/nn/utils/sampling.py
pst/predict/__init__.py
pst/predict/predict.py
pst/training/__init__.py
pst/training/cv.py
pst/training/debug.py
pst/training/finetune.py
pst/training/full.py
pst/training/tuning/__init__.py
pst/training/tuning/manager.py
pst/training/tuning/optuna.py
pst/training/tuning/tuning.py
pst/training/utils/__init__.py
pst/training/utils/constants.py
pst/training/utils/cv.py
pst/training/utils/lightning.py
pst/training/utils/pst.py
pst/utils/__init__.py
pst/utils/_signatures.py
pst/utils/download.py
pst/utils/graphify.py
pst/utils/history.py
pst/utils/versions.py
pst/utils/attrs/converters.py
pst/utils/attrs/dataclass_utils.py
pst/utils/attrs/validators.py
pst/utils/chtc/__init__.py
pst/utils/chtc/cleanup.py
pst/utils/chtc/job.py
pst/utils/chtc/main.py
pst/utils/cli/__init__.py
pst/utils/cli/download.py
pst/utils/cli/experiment.py
pst/utils/cli/finetune.py
pst/utils/cli/graphify.py
pst/utils/cli/modes.py
pst/utils/cli/predict.py
pst/utils/cli/trainer.py
pst/utils/cli/tuning.py
ptn_set_transformer-2.8.0.dist-info/licenses/LICENSE
ptn_set_transformer-2.8.0.dist-info/METADATA
ptn_set_transformer-2.8.0.dist-info/WHEEL
ptn_set_transformer-2.8.0.dist-info/entry_points.txt
ptn_set_transformer-2.8.0.dist-info/top_level.txt
ptn_set_transformer-2.8.0.dist-info/RECORD
