Metadata-Version: 2.4
Name: ptn-set-transformer
Version: 2.8.0
Summary: Training and inference on protein sets (genomes)
Author-email: Cody Martin <codycmar10@gmail.com>
License: MIT License
Project-URL: Homepage, https://github.com/cody-mar10/protein_set_transformer
Project-URL: Bug Tracker, https://github.com/cody-mar10/protein_set_transformer/issues
Classifier: Programming Language :: Python :: 3
Classifier: License :: OSI Approved :: MIT License
Requires-Python: >=3.9
License-File: LICENSE
Requires-Dist: torch>=2
Requires-Dist: transformers>=4.28
Requires-Dist: lightning>=2
Requires-Dist: tables
Requires-Dist: torch_geometric
Requires-Dist: torch_scatter
Requires-Dist: numpy
Requires-Dist: more-itertools
Requires-Dist: lightning-cv[tune]>=1.0
Requires-Dist: optuna>=3.1
Requires-Dist: jsonargparse[signatures]>=4.35.1
Requires-Dist: einops
Requires-Dist: requests
Requires-Dist: tqdm
Requires-Dist: fair-esm==2.0.0
Requires-Dist: scikit-learn
Requires-Dist: typing-extensions>=4.11; python_version < "3.10"
Requires-Dist: attrs>=24.2
Requires-Dist: cattrs>=24.1
Provides-Extra: test
Requires-Dist: pytest>=8.3; extra == "test"
Requires-Dist: pytest-cov; extra == "test"
Provides-Extra: build
Requires-Dist: ruff; extra == "build"
Requires-Dist: mypy; extra == "build"
Requires-Dist: isort; extra == "build"
Requires-Dist: covdefaults; extra == "build"
Provides-Extra: dev
Requires-Dist: ptn-set-transformer[build]; extra == "dev"
Requires-Dist: ptn-set-transformer[test]; extra == "dev"
Dynamic: license-file
